LICENSE
README.rst
pannb/__init__.py
pannb/util.py
pannb-0.1.3.dist-info/entry_points.txt
pannb-0.1.3.dist-info/LICENSE
pannb-0.1.3.dist-info/WHEEL
pannb-0.1.3.dist-info/METADATA
pannb-0.1.3.dist-info/RECORD
