Metadata-Version: 2.1
Name: pannb
Version: 0.1.3
Summary: pannb—pandoc filter for ipynb
Home-page: https://github.com/ickc/pannb
License: BSD-3-Clause
Keywords: pandoc,filter,ipynb
Author: Kolen Cheung
Author-email: christian.kolen@gmail.com
Requires-Python: >=3.8
Classifier: Development Status :: 4 - Beta
Classifier: Environment :: Console
Classifier: Intended Audience :: Developers
Classifier: License :: OSI Approved :: BSD License
Classifier: Operating System :: Microsoft :: Windows
Classifier: Operating System :: POSIX
Classifier: Operating System :: Unix
Classifier: Programming Language :: Python
Classifier: Programming Language :: Python :: 3
Classifier: Programming Language :: Python :: 3.10
Classifier: Programming Language :: Python :: 3.8
Classifier: Programming Language :: Python :: 3.9
Classifier: Programming Language :: Python :: Implementation :: CPython
Classifier: Topic :: Software Development :: Build Tools
Classifier: Topic :: Utilities
Provides-Extra: docs
Provides-Extra: extras
Provides-Extra: tests
Requires-Dist: coloredlogs (>=14,<16); extra == "extras"
Requires-Dist: coverage; extra == "tests"
Requires-Dist: coveralls; extra == "tests"
Requires-Dist: ipykernel; extra == "docs"
Requires-Dist: nbsphinx (>=0.8); extra == "docs"
Requires-Dist: pandas; extra == "docs"
Requires-Dist: panflute (>=2.1.3,<3.0.0)
Requires-Dist: pytest; extra == "tests"
Requires-Dist: sphinx (>=3.3,<4.0); extra == "docs"
Requires-Dist: sphinx-bootstrap-theme; extra == "docs"
Requires-Dist: sphinxcontrib-apidoc; extra == "docs"
Project-URL: Documentation, https://ickc.github.io/pannb
Project-URL: Repository, https://github.com/ickc/pannb
